kitstarter/__init__.py
kitstarter/pindb.py
kitstarter/starter_kits.py
kitstarter/gui/__init__.py
kitstarter/gui/main_window.py
kitstarter/gui/main_window.ui
kitstarter/gui/samples_widget.py
kitstarter/res/arrow-down-disabled.svg
kitstarter/res/arrow-down-enabled.svg
kitstarter/res/arrow-up-disabled.svg
kitstarter/res/arrow-up-enabled.svg
kitstarter/res/delete.svg
kitstarter/res/empty.sfz
kitstarter/res/inst-complete.svg
kitstarter/res/inst-incomplete.svg
kitstarter/res/pin.svg
kitstarter/res/sample-mismatch.svg
kitstarter/res/sample-okay.svg
kitstarter-0.2.3.dist-info/entry_points.txt
kitstarter-0.2.3.dist-info/LICENSE
kitstarter-0.2.3.dist-info/WHEEL
kitstarter-0.2.3.dist-info/METADATA
kitstarter-0.2.3.dist-info/RECORD
