Metadata-Version: 2.1
Name: kitstarter
Version: 0.2.3
Summary: kitstarter is a program you can use to "sketch in" a drumkit SFZ file.
Author-email: Leon Dionne <ldionne@dridesign.sh.cn>
Classifier: License :: OSI Approved :: GNU General Public License v3 or later (GPLv3+)
Requires-Dist: PyQt5
Requires-Dist: soso_qt_extras >= 1.6.0
Requires-Dist: conn_jack
Requires-Dist: midi_notes
Requires-Dist: sfzen >= 1.2.0
Requires-Dist: liquiphy
Requires-Dist: soundfile
Requires-Dist: jack_audio_player
Project-URL: Home, https://github.com/Zen-Master-SoSo/kitstarter
